{"is_source_file": true, "format": "JavaScript", "description": "This file is the entry point for a minimal Bot Framework Echo Bot server. It sets up an Express server, configures the Bot Framework adapter, and defines an EchoBot class that responds to messages by echoing the received text. It includes endpoints for health checks and message processing.", "external_files": ["path", "express", "botbuilder", "dotenv"], "external_methods": ["require('dotenv').config"], "published": ["app", "adapter", "EchoBot"], "classes": [{"name": "EchoBot", "description": "A class extending ActivityHandler that implements a simple echo functionality, responding to messages by echoing back the received text and greeting new members added to the conversation."}], "methods": [{"name": "constructor()", "description": "Initializes the EchoBot class, setting up handlers for message receipt and members added events.", "scope": "EchoBot", "scopeKind": "class"}], "calls": ["express.json()", "adapter.processActivity", "bot.run"], "search-terms": ["index.js", "bot setup", "echo bot", "BotFrameworkAdapter", "ActivityHandler", "health endpoint", "express server"], "state": 2, "file_id": 14, "knowledge_revision": 29, "git_revision": "", "ctags": [{"_type": "tag", "name": "EchoBot", "path": "/home/kavia/workspace/code-generation/teams-message-echo-bot-2761-2828/bot_server/src/index.js", "pattern": "/^class EchoBot extends ActivityHandler {$/", "language": "JavaScript", "kind": "class"}, {"_type": "tag", "name": "PORT", "path": "/home/kavia/workspace/code-generation/teams-message-echo-bot-2761-2828/bot_server/src/index.js", "pattern": "/^const PORT = process.env.BOT_PORT ? Number(process.env.BOT_PORT) : 3978;$/", "language": "JavaScript", "kind": "constant"}, {"_type": "tag", "name": "adapter", "path": "/home/kavia/workspace/code-generation/teams-message-echo-bot-2761-2828/bot_server/src/index.js", "pattern": "/^const adapter = new BotFrameworkAdapter({$/", "language": "JavaScript", "kind": "constant"}, {"_type": "tag", "name": "app", "path": "/home/kavia/workspace/code-generation/teams-message-echo-bot-2761-2828/bot_server/src/index.js", "pattern": "/^const app = express();$/", "language": "JavaScript", "kind": "constant"}, {"_type": "tag", "name": "app", "path": "/home/kavia/workspace/code-generation/teams-message-echo-bot-2761-2828/bot_server/src/index.js", "pattern": "/^module.exports = { app, adapter, EchoBot };$/", "language": "JavaScript", "kind": "field", "scope": "module.exports", "scopeKind": "class"}, {"_type": "tag", "name": "bot", "path": "/home/kavia/workspace/code-generation/teams-message-echo-bot-2761-2828/bot_server/src/index.js", "pattern": "/^const bot = new EchoBot();$/", "language": "JavaScript", "kind": "constant"}, {"_type": "tag", "name": "constructor", "path": "/home/kavia/workspace/code-generation/teams-message-echo-bot-2761-2828/bot_server/src/index.js", "pattern": "/^  constructor() {$/", "language": "JavaScript", "kind": "method", "signature": "()", "scope": "EchoBot", "scopeKind": "class"}, {"_type": "tag", "name": "express", "path": "/home/kavia/workspace/code-generation/teams-message-echo-bot-2761-2828/bot_server/src/index.js", "pattern": "/^const express = require('express');$/", "language": "JavaScript", "kind": "constant"}, {"_type": "tag", "name": "path", "path": "/home/kavia/workspace/code-generation/teams-message-echo-bot-2761-2828/bot_server/src/index.js", "pattern": "/^const path = require('path');$/", "language": "JavaScript", "kind": "constant"}], "hash": "2e9d2d43dce19cac9bd7eb502b50c71b", "format-version": 4, "code-base-name": "teams_echo_bot_frontend", "filename": "bot_server/src/index.js", "fields": [{"name": "module.exports = { app, adapter, EchoBot };", "scope": "module.exports", "scopeKind": "class", "description": "unavailable"}], "revision_history": [{"29": ""}]}